sum04174/__init__.py
sum04174-0.0.1.dist-info/METADATA
sum04174-0.0.1.dist-info/WHEEL
sum04174-0.0.1.dist-info/top_level.txt
sum04174-0.0.1.dist-info/RECORD
