Metadata-Version: 2.1
Name: sum04174
Version: 0.0.1
Summary: 03323019276
Home-page: UNKNOWN
Author: hamza baig
Author-email: mhamza76@yahoo.com
License: UNKNOWN
Platform: UNKNOWN
Classifier: Programming Language :: Python :: 3
Classifier: License :: OSI Approved :: MIT License
Classifier: Operating System :: OS Independent
